anchorestig_static-0.75.5.dist-info/licenses/LICENSE
anchorestigstatic/__init__.py
anchorestigstatic/general.py
anchorestigstatic/generate.py
anchorestigstatic/main.py
anchorestigstatic/provision.py
anchorestigstatic/review.py
anchorestigstatic/static.py
anchorestigstatic/train-k8s-container/CHANGELOG.md
anchorestigstatic/train-k8s-container/Gemfile
anchorestigstatic/train-k8s-container/LICENSE
anchorestigstatic/train-k8s-container/README.md
anchorestigstatic/train-k8s-container/Rakefile
anchorestigstatic/train-k8s-container/VERSION
anchorestigstatic/train-k8s-container/sonar-project.properties
anchorestigstatic/train-k8s-container/train-k8s-container.gemspec
anchorestigstatic/train-k8s-container/.expeditor/config.yml
anchorestigstatic/train-k8s-container/.expeditor/coverage.pipeline.yml
anchorestigstatic/train-k8s-container/.expeditor/update_version.sh
anchorestigstatic/train-k8s-container/.expeditor/verify.pipeline.yml
anchorestigstatic/train-k8s-container/.expeditor/buildkite/coverage.sh
anchorestigstatic/train-k8s-container/.expeditor/buildkite/run_linux_tests.sh
anchorestigstatic/train-k8s-container/docs/README.md
anchorestigstatic/train-k8s-container/lib/train-k8s-container.rb
anchorestigstatic/train-k8s-container/lib/train/k8s/container/connection.rb
anchorestigstatic/train-k8s-container/lib/train/k8s/container/kubectl_exec_client.rb
anchorestigstatic/train-k8s-container/lib/train/k8s/container/platform.rb
anchorestigstatic/train-k8s-container/lib/train/k8s/container/transport.rb
anchorestigstatic/train-k8s-container/lib/train/k8s/container/version.rb
anchorestigstatic/train-k8s-container/spec/spec_helper.rb
anchorestigstatic/train-k8s-container/spec/train/k8s/container_spec.rb
anchorestigstatic/train-k8s-container/spec/train/k8s/kubectl_exec_client_spec.rb
anchorestigstatic/train-k8s-container/spec/train/k8s/container/connection_spec.rb
anchorestigstatic/train-k8s-container/spec/train/k8s/container/platform_spec.rb
anchorestigstatic/train-k8s-container/spec/train/k8s/container/transport_spec.rb
anchorestig_static-0.75.5.dist-info/METADATA
anchorestig_static-0.75.5.dist-info/WHEEL
anchorestig_static-0.75.5.dist-info/entry_points.txt
anchorestig_static-0.75.5.dist-info/top_level.txt
anchorestig_static-0.75.5.dist-info/RECORD
